{
  "heroes": [
    {
      "id": 1,
      "name": "Первый герой",
      "description": "Первый герой в рейтинге!",
      "element": "fire"
    },
    {
      "id": 2,
      "name": "Неизвестный герой",
      "description": "Скрывающийся в тени",
      "element": "wind"
    },
    {
      "id": 3,
      "name": "Морской герой",
      "description": "Как аквамен, но не из DC",
      "element": "water"
    },
    {
      "id": "2ec93dd3-af3f-4e77-a7bd-b080fb3fdd23",
      "name": "ohrannick",
      "description": "all",
      "element": "earth"
    }
  ],
  "filters": [
    {
      "name": "all",
      "label": "Все",
      "className": "btn-outline-dark"
    },
    {
      "name": "fire",
      "label": "Огонь",
      "className": "btn-danger"
    },
    {
      "name": "water",
      "label": "Вода",
      "className": "btn-primary"
    },
    {
      "name": "wind",
      "label": "Ветер",
      "className": "btn-success"
    },
    {
      "name": "earth",
      "label": "Земля",
      "className": "btn-secondary"
    }
  ]
}